tests/cardpanel_demo.py
tests/chat_demo.py
tests/layout_demo.py
tests/multiaiproxy.py
tests/tabs_demo.py
wapyt/__init__.py
wapyt/_runtime.py
wapyt/assets/__init__.py
wapyt/assets/cardpanel.js
wapyt/assets/chat.js
wapyt/assets/layout.js
wapyt/assets/modal.js
wapyt/assets/resourceboard.js
wapyt/assets/sidebar.js
wapyt/assets/tabwidget.js
wapyt/assets/wapyt.css
wapyt/assets/fonts/.keep
wapyt/cardpanel/__init__.py
wapyt/cardpanel/cardpanel.py
wapyt/cardpanel/cardpanel_config.py
wapyt/chat/__init__.py
wapyt/chat/chat.py
wapyt/chat/chat_config.py
wapyt/layout/__init__.py
wapyt/layout/layout.py
wapyt/layout/layout_config.py
wapyt/modal/__init__.py
wapyt/modal/modal.py
wapyt/resourceboard/__init__.py
wapyt/resourceboard/resourceboard.py
wapyt/resourceboard/resourceboard_config.py
wapyt/sidebar/__init__.py
wapyt/sidebar/sidebar.py
wapyt/sidebar/sidebar_config.py
wapyt/tabwidget/__init__.py
wapyt/tabwidget/tabwidget.py
wapyt-0.1.0.dist-info/METADATA
wapyt-0.1.0.dist-info/WHEEL
wapyt-0.1.0.dist-info/top_level.txt
wapyt-0.1.0.dist-info/RECORD
