Metadata-Version: 2.4
Name: wapyt
Version: 0.1.0
Summary: DHTMLX-free PyTincture widgetset with layout, chat, card panel, and tab widgets.
License: MIT
Project-URL: homepage, https://github.com/schapman1974/wA_pytincture_widgetset
Keywords: pytincture,widgetset,pyodide,wapyt
Requires-Python: >=3.13
Requires-Dist: pyodide-py>=0.28.0
Requires-Dist: itsdangerous>=2.2.0
